[
  {
    "line": 1,
    "elements": [
      {
        "start_timestamp": "2021-11-04T05:11:31.905Z",
        "before": [
          {
            "result": {
              "duration": 13674270000,
              "status": "passed"
            },
            "match": {
              "location": "HooksClass.startscenario()"
            }
          },
          {
            "result": {
              "duration": 2428300,
              "status": "passed"
            },
            "match": {
              "location": "HooksClass.starttime()"
            }
          },
          {
            "result": {
              "duration": 303700,
              "status": "passed"
            },
            "match": {
              "location": "HooksClass.success()"
            }
          }
        ],
        "line": 2,
        "name": "To verify forget password functionality",
        "description": "",
        "id": "to-validate-forget-password-feature-in-facebook-page;to-verify-forget-password-functionality",
        "after": [
          {
            "result": {
              "duration": 569300100,
              "status": "passed"
            },
            "match": {
              "location": "HooksClass.sucess(Scenario)"
            }
          },
          {
            "result": {
              "duration": 379900,
              "status": "passed"
            },
            "match": {
              "location": "HooksClass.endtime()"
            }
          },
          {
            "result": {
              "duration": 517401200,
              "status": "passed"
            },
            "match": {
              "location": "HooksClass.endscenario()"
            }
          }
        ],
        "type": "scenario",
        "keyword": "Scenario",
        "steps": [
          {
            "result": {
              "duration": 6653800,
              "status": "passed"
            },
            "line": 3,
            "name": ": The user should launch the chrome browser",
            "match": {
              "location": "FaceBookLoginStepDefinition.the_user_should_launch_the_chrome_browser()"
            },
            "keyword": "Given "
          },
          {
            "result": {
              "duration": 35716100,
              "status": "passed"
            },
            "line": 4,
            "name": ": The user should type the url",
            "match": {
              "location": "FaceBookLoginStepDefinition.the_user_should_type_the_url()"
            },
            "keyword": "When "
          },
          {
            "result": {
              "duration": 2275800,
              "status": "passed"
            },
            "line": 5,
            "name": ": The user should maximaze the window",
            "match": {
              "location": "FaceBookLoginStepDefinition.the_user_should_maximaze_the_window()"
            },
            "keyword": "And "
          },
          {
            "result": {
              "duration": 5254724400,
              "status": "passed"
            },
            "line": 6,
            "name": ": The user should click in forgetpassword link",
            "match": {
              "location": "FacebookForgetPasswordStepDefinition.the_user_should_click_in_forgetpassword_link()"
            },
            "keyword": "And "
          },
          {
            "result": {
              "duration": 20064700,
              "status": "passed"
            },
            "line": 7,
            "name": ": The user should navigate to current page",
            "match": {
              "location": "FacebookForgetPasswordStepDefinition.the_user_should_navigate_to_current_page()"
            },
            "keyword": "And "
          },
          {
            "result": {
              "duration": 296586100,
              "status": "passed"
            },
            "line": 8,
            "name": ": The user should be enter valid mobilenumber or password",
            "match": {
              "location": "FacebookForgetPasswordStepDefinition.the_user_should_be_enter_valid_mobilenumber_or_password()"
            },
            "keyword": "And "
          },
          {
            "result": {
              "duration": 2237096600,
              "status": "passed"
            },
            "line": 9,
            "name": ": The user should be click button",
            "match": {
              "location": "FacebookForgetPasswordStepDefinition.the_user_should_be_click_button()"
            },
            "keyword": "And "
          },
          {
            "result": {
              "duration": 4916434400,
              "status": "passed"
            },
            "line": 10,
            "name": ": The user should navigate to reset password page",
            "match": {
              "location": "FacebookForgetPasswordStepDefinition.the_user_should_navigate_to_reset_password_page()"
            },
            "keyword": "Then "
          }
        ]
      }
    ],
    "name": "To validate forget password feature in facebook page",
    "description": "",
    "id": "to-validate-forget-password-feature-in-facebook-page",
    "keyword": "Feature",
    "uri": "file:src/test/resources/FeatureFile/FacebookForget.feature",
    "tags": []
  },
  {
    "line": 2,
    "elements": [
      {
        "line": 3,
        "name": "",
        "description": "",
        "type": "background",
        "keyword": "Background",
        "steps": [
          {
            "result": {
              "duration": 3663000,
              "status": "passed"
            },
            "line": 4,
            "name": ": The user should launch the chrome browser",
            "match": {
              "location": "FaceBookLoginStepDefinition.the_user_should_launch_the_chrome_browser()"
            },
            "keyword": "Given "
          },
          {
            "result": {
              "duration": 2188300,
              "status": "passed"
            },
            "line": 5,
            "name": ": The user should type the url",
            "match": {
              "location": "FaceBookLoginStepDefinition.the_user_should_type_the_url()"
            },
            "keyword": "When "
          },
          {
            "result": {
              "duration": 2721600,
              "status": "passed"
            },
            "line": 6,
            "name": ": The user should maximaze the window",
            "match": {
              "location": "FaceBookLoginStepDefinition.the_user_should_maximaze_the_window()"
            },
            "keyword": "And "
          }
        ]
      },
      {
        "start_timestamp": "2021-11-04T05:11:59.584Z",
        "before": [
          {
            "result": {
              "duration": 7678229400,
              "status": "passed"
            },
            "match": {
              "location": "HooksClass.startscenario()"
            }
          },
          {
            "result": {
              "duration": 618800,
              "status": "passed"
            },
            "match": {
              "location": "HooksClass.starttime()"
            }
          },
          {
            "result": {
              "duration": 346200,
              "status": "passed"
            },
            "match": {
              "location": "HooksClass.success()"
            }
          }
        ],
        "line": 8,
        "name": "Validate with invalid username and valid password",
        "description": "",
        "id": "to-validate-login-functionlity-of-facebook;validate-with-invalid-username-and-valid-password",
        "after": [
          {
            "result": {
              "duration": 251366200,
              "status": "passed"
            },
            "match": {
              "location": "HooksClass.sucess(Scenario)"
            }
          },
          {
            "result": {
              "duration": 232900,
              "status": "passed"
            },
            "match": {
              "location": "HooksClass.endtime()"
            }
          },
          {
            "result": {
              "duration": 371308600,
              "status": "passed"
            },
            "match": {
              "location": "HooksClass.endscenario()"
            }
          }
        ],
        "type": "scenario",
        "keyword": "Scenario",
        "steps": [
          {
            "result": {
              "duration": 576899700,
              "status": "passed"
            },
            "line": 9,
            "name": ": The user should type the invalid username and valid passwords",
            "match": {
              "location": "FaceBookLoginStepDefinition.the_user_should_type_the_invalid_username_and_valid_passwords(DataTable)"
            },
            "rows": [
              {
                "cells": [
                  "user",
                  "pass",
                  "storage",
                  "ram"
                ]
              },
              {
                "cells": [
                  "dhoni",
                  "dhoni@123",
                  "jeeva",
                  "jeeva@123"
                ]
              },
              {
                "cells": [
                  "arun",
                  "arun@123",
                  "ajith",
                  "ajith@123"
                ]
              },
              {
                "cells": [
                  "kholi",
                  "kholi@123",
                  "raina",
                  "raina@123"
                ]
              }
            ],
            "keyword": "And "
          },
          {
            "result": {
              "duration": 2146041800,
              "status": "passed"
            },
            "line": 15,
            "name": ": The user should click the login button",
            "match": {
              "location": "FaceBookLoginStepDefinition.the_user_should_click_the_login_button()"
            },
            "keyword": "And "
          },
          {
            "result": {
              "duration": 24917626200,
              "status": "passed"
            },
            "line": 16,
            "name": ": The user should naviage to incorrect credential page",
            "match": {
              "location": "FaceBookLoginStepDefinition.the_user_should_naviage_to_incorrect_credential_page()"
            },
            "keyword": "Then "
          }
        ]
      },
      {
        "line": 3,
        "name": "",
        "description": "",
        "type": "background",
        "keyword": "Background",
        "steps": [
          {
            "result": {
              "duration": 2346400,
              "status": "passed"
            },
            "line": 4,
            "name": ": The user should launch the chrome browser",
            "match": {
              "location": "FaceBookLoginStepDefinition.the_user_should_launch_the_chrome_browser()"
            },
            "keyword": "Given "
          },
          {
            "result": {
              "duration": 2008100,
              "status": "passed"
            },
            "line": 5,
            "name": ": The user should type the url",
            "match": {
              "location": "FaceBookLoginStepDefinition.the_user_should_type_the_url()"
            },
            "keyword": "When "
          },
          {
            "result": {
              "duration": 3201500,
              "status": "passed"
            },
            "line": 6,
            "name": ": The user should maximaze the window",
            "match": {
              "location": "FaceBookLoginStepDefinition.the_user_should_maximaze_the_window()"
            },
            "keyword": "And "
          }
        ]
      },
      {
        "start_timestamp": "2021-11-04T05:12:35.567Z",
        "before": [
          {
            "result": {
              "duration": 6864114600,
              "status": "passed"
            },
            "match": {
              "location": "HooksClass.startscenario()"
            }
          },
          {
            "result": {
              "duration": 374600,
              "status": "passed"
            },
            "match": {
              "location": "HooksClass.starttime()"
            }
          },
          {
            "result": {
              "duration": 241500,
              "status": "passed"
            },
            "match": {
              "location": "HooksClass.success()"
            }
          }
        ],
        "line": 26,
        "name": "Validate with invalid username and invalid password",
        "description": "",
        "id": "to-validate-login-functionlity-of-facebook;validate-with-invalid-username-and-invalid-password;;2",
        "after": [
          {
            "result": {
              "duration": 212962100,
              "status": "passed"
            },
            "match": {
              "location": "HooksClass.sucess(Scenario)"
            }
          },
          {
            "result": {
              "duration": 258000,
              "status": "passed"
            },
            "match": {
              "location": "HooksClass.endtime()"
            }
          },
          {
            "result": {
              "duration": 441525700,
              "status": "passed"
            },
            "match": {
              "location": "HooksClass.endscenario()"
            }
          }
        ],
        "type": "scenario",
        "keyword": "Scenario Outline",
        "steps": [
          {
            "result": {
              "duration": 447374800,
              "status": "passed"
            },
            "line": 20,
            "name": ": The user should type the invalid username \"arun\" and invalid password \"arun@1996\"",
            "match": {
              "arguments": [
                {
                  "val": "\"arun\"",
                  "offset": 44
                },
                {
                  "val": "\"arun@1996\"",
                  "offset": 72
                }
              ],
              "location": "FaceBookLoginStepDefinition.the_user_should_type_the_invalid_username_and_invalid_password(String,String)"
            },
            "keyword": "And "
          },
          {
            "result": {
              "duration": 2156541200,
              "status": "passed"
            },
            "line": 21,
            "name": ": The user should click the login button",
            "match": {
              "location": "FaceBookLoginStepDefinition.the_user_should_click_the_login_button()"
            },
            "keyword": "And "
          },
          {
            "result": {
              "duration": 2096671100,
              "status": "passed"
            },
            "line": 22,
            "name": ": The user should naviage to incorrect credential page",
            "match": {
              "location": "FaceBookLoginStepDefinition.the_user_should_naviage_to_incorrect_credential_page()"
            },
            "keyword": "Then "
          }
        ]
      },
      {
        "line": 3,
        "name": "",
        "description": "",
        "type": "background",
        "keyword": "Background",
        "steps": [
          {
            "result": {
              "duration": 1751000,
              "status": "passed"
            },
            "line": 4,
            "name": ": The user should launch the chrome browser",
            "match": {
              "location": "FaceBookLoginStepDefinition.the_user_should_launch_the_chrome_browser()"
            },
            "keyword": "Given "
          },
          {
            "result": {
              "duration": 2577500,
              "status": "passed"
            },
            "line": 5,
            "name": ": The user should type the url",
            "match": {
              "location": "FaceBookLoginStepDefinition.the_user_should_type_the_url()"
            },
            "keyword": "When "
          },
          {
            "result": {
              "duration": 1950400,
              "status": "passed"
            },
            "line": 6,
            "name": ": The user should maximaze the window",
            "match": {
              "location": "FaceBookLoginStepDefinition.the_user_should_maximaze_the_window()"
            },
            "keyword": "And "
          }
        ]
      },
      {
        "start_timestamp": "2021-11-04T05:12:47.826Z",
        "before": [
          {
            "result": {
              "duration": 6613629300,
              "status": "passed"
            },
            "match": {
              "location": "HooksClass.startscenario()"
            }
          },
          {
            "result": {
              "duration": 323300,
              "status": "passed"
            },
            "match": {
              "location": "HooksClass.starttime()"
            }
          },
          {
            "result": {
              "duration": 117600,
              "status": "passed"
            },
            "match": {
              "location": "HooksClass.success()"
            }
          }
        ],
        "line": 27,
        "name": "Validate with invalid username and invalid password",
        "description": "",
        "id": "to-validate-login-functionlity-of-facebook;validate-with-invalid-username-and-invalid-password;;3",
        "after": [
          {
            "result": {
              "duration": 291994000,
              "status": "passed"
            },
            "match": {
              "location": "HooksClass.sucess(Scenario)"
            }
          },
          {
            "result": {
              "duration": 226300,
              "status": "passed"
            },
            "match": {
              "location": "HooksClass.endtime()"
            }
          },
          {
            "result": {
              "duration": 585387900,
              "status": "passed"
            },
            "match": {
              "location": "HooksClass.endscenario()"
            }
          }
        ],
        "type": "scenario",
        "keyword": "Scenario Outline",
        "steps": [
          {
            "result": {
              "duration": 460968400,
              "status": "passed"
            },
            "line": 20,
            "name": ": The user should type the invalid username \"ajith\" and invalid password \"ajith@123\"",
            "match": {
              "arguments": [
                {
                  "val": "\"ajith\"",
                  "offset": 44
                },
                {
                  "val": "\"ajith@123\"",
                  "offset": 73
                }
              ],
              "location": "FaceBookLoginStepDefinition.the_user_should_type_the_invalid_username_and_invalid_password(String,String)"
            },
            "keyword": "And "
          },
          {
            "result": {
              "duration": 2161702400,
              "status": "passed"
            },
            "line": 21,
            "name": ": The user should click the login button",
            "match": {
              "location": "FaceBookLoginStepDefinition.the_user_should_click_the_login_button()"
            },
            "keyword": "And "
          },
          {
            "result": {
              "duration": 25980159600,
              "status": "passed"
            },
            "line": 22,
            "name": ": The user should naviage to incorrect credential page",
            "match": {
              "location": "FaceBookLoginStepDefinition.the_user_should_naviage_to_incorrect_credential_page()"
            },
            "keyword": "Then "
          }
        ]
      },
      {
        "line": 3,
        "name": "",
        "description": "",
        "type": "background",
        "keyword": "Background",
        "steps": [
          {
            "result": {
              "duration": 3300700,
              "status": "passed"
            },
            "line": 4,
            "name": ": The user should launch the chrome browser",
            "match": {
              "location": "FaceBookLoginStepDefinition.the_user_should_launch_the_chrome_browser()"
            },
            "keyword": "Given "
          },
          {
            "result": {
              "duration": 2473800,
              "status": "passed"
            },
            "line": 5,
            "name": ": The user should type the url",
            "match": {
              "location": "FaceBookLoginStepDefinition.the_user_should_type_the_url()"
            },
            "keyword": "When "
          },
          {
            "result": {
              "duration": 2145200,
              "status": "passed"
            },
            "line": 6,
            "name": ": The user should maximaze the window",
            "match": {
              "location": "FaceBookLoginStepDefinition.the_user_should_maximaze_the_window()"
            },
            "keyword": "And "
          }
        ]
      },
      {
        "start_timestamp": "2021-11-04T05:13:23.935Z",
        "before": [
          {
            "result": {
              "duration": 6700525400,
              "status": "passed"
            },
            "match": {
              "location": "HooksClass.startscenario()"
            }
          },
          {
            "result": {
              "duration": 382800,
              "status": "passed"
            },
            "match": {
              "location": "HooksClass.starttime()"
            }
          },
          {
            "result": {
              "duration": 3074500,
              "status": "passed"
            },
            "match": {
              "location": "HooksClass.success()"
            }
          }
        ],
        "line": 28,
        "name": "Validate with invalid username and invalid password",
        "description": "",
        "id": "to-validate-login-functionlity-of-facebook;validate-with-invalid-username-and-invalid-password;;4",
        "after": [
          {
            "result": {
              "duration": 241212200,
              "status": "passed"
            },
            "match": {
              "location": "HooksClass.sucess(Scenario)"
            }
          },
          {
            "result": {
              "duration": 236200,
              "status": "passed"
            },
            "match": {
              "location": "HooksClass.endtime()"
            }
          },
          {
            "result": {
              "duration": 4273351200,
              "status": "passed"
            },
            "match": {
              "location": "HooksClass.endscenario()"
            }
          }
        ],
        "type": "scenario",
        "keyword": "Scenario Outline",
        "steps": [
          {
            "result": {
              "duration": 525756000,
              "status": "passed"
            },
            "line": 20,
            "name": ": The user should type the invalid username \"dhoni\" and invalid password \"dhoni@123\"",
            "match": {
              "arguments": [
                {
                  "val": "\"dhoni\"",
                  "offset": 44
                },
                {
                  "val": "\"dhoni@123\"",
                  "offset": 73
                }
              ],
              "location": "FaceBookLoginStepDefinition.the_user_should_type_the_invalid_username_and_invalid_password(String,String)"
            },
            "keyword": "And "
          },
          {
            "result": {
              "duration": 2163040900,
              "status": "passed"
            },
            "line": 21,
            "name": ": The user should click the login button",
            "match": {
              "location": "FaceBookLoginStepDefinition.the_user_should_click_the_login_button()"
            },
            "keyword": "And "
          },
          {
            "result": {
              "duration": 19896831000,
              "status": "passed"
            },
            "line": 22,
            "name": ": The user should naviage to incorrect credential page",
            "match": {
              "location": "FaceBookLoginStepDefinition.the_user_should_naviage_to_incorrect_credential_page()"
            },
            "keyword": "Then "
          }
        ]
      }
    ],
    "name": "To validate login functionlity of facebook",
    "description": "",
    "id": "to-validate-login-functionlity-of-facebook",
    "keyword": "Feature",
    "uri": "file:src/test/resources/FeatureFile/FaceboolLogin.feature",
    "tags": []
  }
]